uipath_connectors/google_gmail/__init__.py
uipath_connectors/google_gmail/client.py
uipath_connectors/google_gmail/errors.py
uipath_connectors/google_gmail/py.typed
uipath_connectors/google_gmail/types.py
uipath_connectors/google_gmail/api/__init__.py
uipath_connectors/google_gmail/api/apply_gmail_label/__init__.py
uipath_connectors/google_gmail/api/apply_gmail_label/apply_gmail_label.py
uipath_connectors/google_gmail/api/archive_email/__init__.py
uipath_connectors/google_gmail/api/archive_email/archive_email.py
uipath_connectors/google_gmail/api/calendar/__init__.py
uipath_connectors/google_gmail/api/calendar/get_event_by_id.py
uipath_connectors/google_gmail/api/create_calendar_event/__init__.py
uipath_connectors/google_gmail/api/create_calendar_event/create_calendar_event.py
uipath_connectors/google_gmail/api/curated_calendar_list/__init__.py
uipath_connectors/google_gmail/api/curated_calendar_list/get_calendar_list.py
uipath_connectors/google_gmail/api/delete_email/__init__.py
uipath_connectors/google_gmail/api/delete_email/delete_email.py
uipath_connectors/google_gmail/api/download_attachment/__init__.py
uipath_connectors/google_gmail/api/download_attachment/download_attachment.py
uipath_connectors/google_gmail/api/download_email/__init__.py
uipath_connectors/google_gmail/api/download_email/download_email.py
uipath_connectors/google_gmail/api/email_reply/__init__.py
uipath_connectors/google_gmail/api/email_reply/reply_to_email_v2.py
uipath_connectors/google_gmail/api/folder/__init__.py
uipath_connectors/google_gmail/api/folder/get_email_labels.py
uipath_connectors/google_gmail/api/folder/get_single_label_by_id.py
uipath_connectors/google_gmail/api/forward_event/__init__.py
uipath_connectors/google_gmail/api/forward_event/forward_event.py
uipath_connectors/google_gmail/api/forward_mail_v2/__init__.py
uipath_connectors/google_gmail/api/forward_mail_v2/forward_mail_v2.py
uipath_connectors/google_gmail/api/get_newest_email/__init__.py
uipath_connectors_google_gmail-1.19.1.dev12.dist-info/METADATA
uipath_connectors_google_gmail-1.19.1.dev12.dist-info/WHEEL
uipath_connectors_google_gmail-1.19.1.dev12.dist-info/entry_points.txt
uipath_connectors_google_gmail-1.19.1.dev12.dist-info/top_level.txt
uipath_connectors_google_gmail-1.19.1.dev12.dist-info/RECORD
